{
  "_class": "group",
  "do_objectID": "8454641D-961A-4498-9421-F3AA7B330F82",
  "exportOptions": {
    "_class": "exportOptions",
    "exportFormats": [],
    "includedLayerIds": [],
    "layerOptions": 0,
    "shouldTrim": false
  },
  "frame": {
    "_class": "rect",
    "constrainProportions": false,
    "height": 46,
    "width": 359,
    "x": 8,
    "y": 412
  },
  "isFlippedHorizontal": false,
  "isFlippedVertical": false,
  "isLocked": false,
  "isVisible": true,
  "layerListExpandedType": 2,
  "name": "btn",
  "nameIsFixed": true,
  "resizingConstraint": 63,
  "resizingType": 0,
  "rotation": 0,
  "shouldBreakMaskChain": false,
  "style": {
    "_class": "style",
    "endDecorationType": 0,
    "miterLimit": 10,
    "startDecorationType": 0
  },
  "hasClickThrough": false,
  "layers": [
    {
      "id": "FB904DB9-FE3C-4729-8C74-DD7C0E80ECCB",
      "class": "shapeGroup"
    },
    {
      "id": "B556EB28-DC93-44F9-BA95-128DD5421314",
      "class": "text"
    }
  ]
}