{
  "_class": "shapeGroup",
  "do_objectID": "70823CD4-9032-4936-B669-77BEC6B185EF",
  "exportOptions": {
    "_class": "exportOptions",
    "exportFormats": [],
    "includedLayerIds": [],
    "layerOptions": 0,
    "shouldTrim": false
  },
  "frame": {
    "_class": "rect",
    "constrainProportions": false,
    "height": 11.91828571428572,
    "width": 11.91819047619048,
    "x": 0.04085714285714034,
    "y": 0.04085714285714306
  },
  "isFlippedHorizontal": false,
  "isFlippedVertical": false,
  "isLocked": false,
  "isVisible": true,
  "layerListExpandedType": 1,
  "name": "Shape",
  "nameIsFixed": false,
  "originalObjectID": "7A09F8E2-0FED-4878-9235-4A782DDD048F",
  "resizingConstraint": 63,
  "resizingType": 0,
  "rotation": 0,
  "shouldBreakMaskChain": false,
  "style": {
    "_class": "style",
    "endDecorationType": 0,
    "fills": [
      {
        "_class": "fill",
        "isEnabled": true,
        "color": {
          "_class": "color",
          "alpha": 1,
          "blue": 1,
          "green": 1,
          "red": 1
        },
        "fillType": 0,
        "noiseIndex": 0,
        "noiseIntensity": 0,
        "patternFillType": 0,
        "patternTileScale": 1
      }
    ],
    "miterLimit": 10,
    "startDecorationType": 0
  },
  "hasClickThrough": false,
  "layers": [
    {
      "id": "1DC8B0A2-CD8E-47CA-9087-A395BF03AB3C",
      "class": "shapePath"
    },
    {
      "id": "FF96A02F-51F8-40A7-9595-6642242C9BC0",
      "class": "shapePath"
    },
    {
      "id": "6CE7CDC4-CD26-4F74-8F00-79A9EB4E1847",
      "class": "shapePath"
    },
    {
      "id": "3652942B-DE9C-4258-AF75-54A7075E87E1",
      "class": "shapePath"
    }
  ],
  "clippingMaskMode": 0,
  "hasClippingMask": false,
  "windingRule": 1
}