{
  "_class": "shapeGroup",
  "do_objectID": "2CD82D9D-4FD8-44A1-9720-E8C01EFC6B50",
  "exportOptions": {
    "_class": "exportOptions",
    "exportFormats": [],
    "includedLayerIds": [],
    "layerOptions": 0,
    "shouldTrim": false
  },
  "frame": {
    "_class": "rect",
    "constrainProportions": false,
    "height": 2,
    "width": 155,
    "x": 0,
    "y": 4
  },
  "isFlippedHorizontal": false,
  "isFlippedVertical": false,
  "isLocked": false,
  "isVisible": true,
  "layerListExpandedType": 0,
  "name": "Line",
  "nameIsFixed": false,
  "resizingConstraint": 63,
  "resizingType": 0,
  "rotation": 0,
  "shouldBreakMaskChain": false,
  "style": {
    "_class": "style",
    "borderOptions": {
      "_class": "borderOptions",
      "isEnabled": false,
      "dashPattern": [
        6,
        12
      ],
      "lineCapStyle": 2,
      "lineJoinStyle": 0
    },
    "borders": [
      {
        "_class": "border",
        "isEnabled": true,
        "color": {
          "_class": "color",
          "alpha": 1,
          "blue": 0.9490196078431372,
          "green": 0.2745098039215689,
          "red": 0.1254901960784314
        },
        "fillType": 0,
        "position": 0,
        "thickness": 3
      }
    ],
    "endDecorationType": 0,
    "fills": [
      {
        "_class": "fill",
        "isEnabled": false,
        "color": {
          "_class": "color",
          "alpha": 1,
          "blue": 0.847,
          "green": 0.847,
          "red": 0.847
        },
        "fillType": 0,
        "noiseIndex": 0,
        "noiseIntensity": 0,
        "patternFillType": 1,
        "patternTileScale": 1
      }
    ],
    "miterLimit": 10,
    "shadows": [
      {
        "_class": "shadow",
        "isEnabled": false,
        "blurRadius": 4,
        "color": {
          "_class": "color",
          "alpha": 0.5,
          "blue": 0,
          "green": 0,
          "red": 0
        },
        "contextSettings": {
          "_class": "graphicsContextSettings",
          "blendMode": 0,
          "opacity": 1
        },
        "offsetX": 0,
        "offsetY": 2,
        "spread": 0
      }
    ],
    "sharedObjectID": "DE877BAA-3A92-45F3-B90A-24061CDF3593",
    "startDecorationType": 0
  },
  "hasClickThrough": false,
  "layers": [
    {
      "id": "75788CA6-46EA-4AC6-85ED-C0E949E8E7BA",
      "class": "shapePath"
    }
  ],
  "clippingMaskMode": 0,
  "hasClippingMask": false,
  "windingRule": 1
}